morpho_symm/__init__.py
morpho_symm/dynamics_harmonics_analysis.py
morpho_symm/robot_symmetry_visualization.py
morpho_symm/robot_symmetry_visualization_dynamic.py
morpho_symm/cfg/config.yaml
morpho_symm/cfg/config_visualization.yaml
morpho_symm/cfg/dataset/com_momentum.yaml
morpho_symm/cfg/dataset/contact.yaml
morpho_symm/cfg/model/base_model.yaml
morpho_symm/cfg/model/contact_cnn.yaml
morpho_symm/cfg/model/contact_ecnn.yaml
morpho_symm/cfg/model/emlp.yaml
morpho_symm/cfg/model/mlp.yaml
morpho_symm/cfg/robot/a1.yaml
morpho_symm/cfg/robot/aliengo.yaml
morpho_symm/cfg/robot/anymal_b-c2.yaml
morpho_symm/cfg/robot/anymal_b.yaml
morpho_symm/cfg/robot/anymal_c-c2.yaml
morpho_symm/cfg/robot/anymal_c.yaml
morpho_symm/cfg/robot/atlas.yaml
morpho_symm/cfg/robot/b1.yaml
morpho_symm/cfg/robot/base_robot.yaml
morpho_symm/cfg/robot/baxter.yaml
morpho_symm/cfg/robot/bolt.yaml
morpho_symm/cfg/robot/cassie.yaml
morpho_symm/cfg/robot/ergocub.yaml
morpho_symm/cfg/robot/go1.yaml
morpho_symm/cfg/robot/go2.yaml
morpho_symm/cfg/robot/hyq-c2.yaml
morpho_symm/cfg/robot/hyq.yaml
morpho_symm/cfg/robot/iiwa.yaml
morpho_symm/cfg/robot/mini_cheetah-c2.yaml
morpho_symm/cfg/robot/mini_cheetah-k4.yaml
morpho_symm/cfg/robot/mini_cheetah.yaml
morpho_symm/cfg/robot/solo-c2.yaml
morpho_symm/cfg/robot/solo-k4.yaml
morpho_symm/cfg/robot/solo.yaml
morpho_symm/cfg/robot/trifinger.yaml
morpho_symm/cfg/robot/upkie.yaml
morpho_symm/cfg/robot/ur10.yaml
morpho_symm/cfg/robot/ur3.yaml
morpho_symm/cfg/robot/ur5.yaml
morpho_symm/data/DynamicsRecording.py
morpho_symm/data/__init__.py
morpho_symm/data/com_momentum/com_momentum.py
morpho_symm/data/contact_dataset/umich_contact_dataset.py
morpho_symm/data/mini_cheetah/read_recordings.py
morpho_symm/data/mini_cheetah/raysim_recordings/uneven_easy/Screenshot from 2023-11-24 15-20-20.png
morpho_symm/data/mini_cheetah/raysim_recordings/uneven_medium/Screenshot from 2023-11-24 15-10-56.png
morpho_symm/data/mini_cheetah/sampling_based_controller/simple_read.py
morpho_symm-0.1.10.dist-info/METADATA
morpho_symm-0.1.10.dist-info/WHEEL
morpho_symm-0.1.10.dist-info/entry_points.txt
morpho_symm-0.1.10.dist-info/licenses/LICENSE
morpho_symm-0.1.10.dist-info/RECORD
