Metadata-Version: 2.4
Name: morpho-symm
Version: 0.1.10
Summary: Tools for the identification, study, and exploitation of morphological symmetries in robotics
Project-URL: Homepage, https://github.com/Danfoa/MorphoSymm
Project-URL: Bug Tracker, https://github.com/Danfoa/MorphoSymm/issues
Author-email: Daniel Ordoñez-Apraez <daniels.ordonez@gmail.com>
Maintainer-email: Daniel Ordoñez-Apraez <daniels.ordonez@gmail.com>
License-File: LICENSE
Keywords: dynamical systems,locomotion,morphological symmetry,robot symmetries,symmetry
Classifier: Development Status :: 4 - Beta
Classifier: License :: OSI Approved :: MIT License
Classifier: Operating System :: OS Independent
Classifier: Programming Language :: Python :: 3
Requires-Python: >=3.8
Requires-Dist: escnn>=1.0.0
Requires-Dist: hydra-core
Requires-Dist: networkx>=2.5
Requires-Dist: pytest
Requires-Dist: robot-descriptions
Requires-Dist: scipy>=1.6
Provides-Extra: pin
Requires-Dist: pin<3.0,>=2.6; extra == 'pin'
Requires-Dist: pybullet; extra == 'pin'
